[
    {
        "Station": "work02",
        "id": "000",
        "Lat": 111.0,
        "Long": 222.0,
        "Radius": 3.0,
        "Duration": 600.0,
        "Sample": 153600.0
    },
    {
        "Station": "work02",
        "id": "001",
        "Lat": 111.0,
        "Long": 222.0,
        "Radius": 3.0,
        "Duration": 600.0,
        "Sample": 153600.0
    },
    {
        "Station": "work02",
        "id": "002",
        "Lat": 111.0,
        "Long": 222.0,
        "Radius": 3.0,
        "Duration": 900.0,
        "Sample": 230400.0
    },
    {
        "Station": "work02",
        "id": "003",
        "Lat": 231.0,
        "Long": 234.0,
        "Radius": 6.0,
        "Duration": 600.0,
        "Sample": 153600.0
    },
    {
        "Station": "work02",
        "id": "004",
        "Lat": 992.0,
        "Long": 321.0,
        "Radius": 12.0,
        "Duration": 600.0,
        "Sample": 153600.0
    }
]